{
  "name": "Team_062",
  "target_overall_rating": 58,
  "actual_overall_rating": 54.3,
  "roster": [
    {
      "name": "Chris Bird",
      "position": "PG",
      "grip_strength": 38,
      "arm_strength": 64,
      "core_strength": 56,
      "agility": 65,
      "acceleration": 72,
      "top_speed": 59,
      "jumping": 52,
      "reactions": 70,
      "stamina": 63,
      "balance": 63,
      "height": 33,
      "durability": 57,
      "awareness": 67,
      "creativity": 68,
      "determination": 74,
      "bravery": 57,
      "consistency": 55,
      "composure": 67,
      "patience": 59,
      "hand_eye_coordination": 50,
      "throw_accuracy": 76,
      "form_technique": 46,
      "finesse": 65,
      "deception": 58,
      "teamwork": 63
    },
    {
      "name": "RJ Williamson",
      "position": "SG",
      "grip_strength": 69,
      "arm_strength": 39,
      "core_strength": 43,
      "agility": 80,
      "acceleration": 56,
      "top_speed": 70,
      "jumping": 49,
      "reactions": 56,
      "stamina": 59,
      "balance": 67,
      "height": 49,
      "durability": 18,
      "awareness": 55,
      "creativity": 62,
      "determination": 39,
      "bravery": 40,
      "consistency": 42,
      "composure": 41,
      "patience": 36,
      "hand_eye_coordination": 48,
      "throw_accuracy": 59,
      "form_technique": 43,
      "finesse": 56,
      "deception": 59,
      "teamwork": 92
    },
    {
      "name": "Michael Hyland",
      "position": "SF",
      "grip_strength": 47,
      "arm_strength": 48,
      "core_strength": 68,
      "agility": 54,
      "acceleration": 49,
      "top_speed": 82,
      "jumping": 68,
      "reactions": 65,
      "stamina": 60,
      "balance": 69,
      "height": 51,
      "durability": 54,
      "awareness": 46,
      "creativity": 46,
      "determination": 59,
      "bravery": 57,
      "consistency": 54,
      "composure": 46,
      "patience": 47,
      "hand_eye_coordination": 75,
      "throw_accuracy": 47,
      "form_technique": 72,
      "finesse": 56,
      "deception": 63,
      "teamwork": 77
    },
    {
      "name": "Kawhi Thompson",
      "position": "PF",
      "grip_strength": 73,
      "arm_strength": 71,
      "core_strength": 51,
      "agility": 57,
      "acceleration": 32,
      "top_speed": 57,
      "jumping": 71,
      "reactions": 41,
      "stamina": 69,
      "balance": 69,
      "height": 74,
      "durability": 60,
      "awareness": 71,
      "creativity": 67,
      "determination": 69,
      "bravery": 79,
      "consistency": 62,
      "composure": 51,
      "patience": 51,
      "hand_eye_coordination": 67,
      "throw_accuracy": 65,
      "form_technique": 47,
      "finesse": 50,
      "deception": 46,
      "teamwork": 70
    },
    {
      "name": "Jalen Reaves",
      "position": "C",
      "grip_strength": 83,
      "arm_strength": 53,
      "core_strength": 68,
      "agility": 34,
      "acceleration": 36,
      "top_speed": 55,
      "jumping": 79,
      "reactions": 61,
      "stamina": 57,
      "balance": 61,
      "height": 77,
      "durability": 54,
      "awareness": 47,
      "creativity": 54,
      "determination": 64,
      "bravery": 53,
      "consistency": 66,
      "composure": 44,
      "patience": 61,
      "hand_eye_coordination": 44,
      "throw_accuracy": 45,
      "form_technique": 57,
      "finesse": 53,
      "deception": 23,
      "teamwork": 63
    },
    {
      "name": "Paolo McCollum",
      "position": "PG",
      "grip_strength": 45,
      "arm_strength": 46,
      "core_strength": 21,
      "agility": 64,
      "acceleration": 36,
      "top_speed": 64,
      "jumping": 60,
      "reactions": 58,
      "stamina": 50,
      "balance": 45,
      "height": 36,
      "durability": 42,
      "awareness": 54,
      "creativity": 71,
      "determination": 60,
      "bravery": 46,
      "consistency": 48,
      "composure": 62,
      "patience": 61,
      "hand_eye_coordination": 51,
      "throw_accuracy": 84,
      "form_technique": 56,
      "finesse": 47,
      "deception": 73,
      "teamwork": 46
    },
    {
      "name": "Tony LaVine",
      "position": "SG",
      "grip_strength": 32,
      "arm_strength": 56,
      "core_strength": 40,
      "agility": 48,
      "acceleration": 62,
      "top_speed": 61,
      "jumping": 53,
      "reactions": 51,
      "stamina": 34,
      "balance": 77,
      "height": 9,
      "durability": 51,
      "awareness": 40,
      "creativity": 49,
      "determination": 53,
      "bravery": 57,
      "consistency": 58,
      "composure": 23,
      "patience": 66,
      "hand_eye_coordination": 60,
      "throw_accuracy": 47,
      "form_technique": 58,
      "finesse": 47,
      "deception": 18,
      "teamwork": 71
    },
    {
      "name": "Paul Poole",
      "position": "SF",
      "grip_strength": 70,
      "arm_strength": 28,
      "core_strength": 36,
      "agility": 34,
      "acceleration": 61,
      "top_speed": 76,
      "jumping": 56,
      "reactions": 18,
      "stamina": 69,
      "balance": 46,
      "height": 54,
      "durability": 65,
      "awareness": 75,
      "creativity": 71,
      "determination": 65,
      "bravery": 59,
      "consistency": 52,
      "composure": 45,
      "patience": 52,
      "hand_eye_coordination": 57,
      "throw_accuracy": 42,
      "form_technique": 56,
      "finesse": 65,
      "deception": 44,
      "teamwork": 50
    },
    {
      "name": "RJ Wall",
      "position": "PF",
      "grip_strength": 74,
      "arm_strength": 64,
      "core_strength": 76,
      "agility": 46,
      "acceleration": 43,
      "top_speed": 56,
      "jumping": 46,
      "reactions": 51,
      "stamina": 65,
      "balance": 65,
      "height": 59,
      "durability": 42,
      "awareness": 62,
      "creativity": 41,
      "determination": 59,
      "bravery": 30,
      "consistency": 69,
      "composure": 57,
      "patience": 45,
      "hand_eye_coordination": 56,
      "throw_accuracy": 37,
      "form_technique": 62,
      "finesse": 45,
      "deception": 50,
      "teamwork": 62
    },
    {
      "name": "Devin Young",
      "position": "C",
      "grip_strength": 87,
      "arm_strength": 71,
      "core_strength": 62,
      "agility": 41,
      "acceleration": 31,
      "top_speed": 46,
      "jumping": 38,
      "reactions": 46,
      "stamina": 19,
      "balance": 47,
      "height": 54,
      "durability": 61,
      "awareness": 47,
      "creativity": 25,
      "determination": 67,
      "bravery": 60,
      "consistency": 40,
      "composure": 44,
      "patience": 71,
      "hand_eye_coordination": 48,
      "throw_accuracy": 30,
      "form_technique": 68,
      "finesse": 49,
      "deception": 28,
      "teamwork": 48
    }
  ]
}